ShiyanlouNosqlJiaochengHeji20160904/README.md
ShiyanlouNosqlJiaochengHeji20160904/__init__.py
ShiyanlouNosqlJiaochengHeji20160904/__main__.py
ShiyanlouNosqlJiaochengHeji20160904/file.epub
ShiyanlouNosqlJiaochengHeji20160904/index.html
ShiyanlouNosqlJiaochengHeji20160904/css/__init__.py
ShiyanlouNosqlJiaochengHeji20160904/css/annotations.css
ShiyanlouNosqlJiaochengHeji20160904/css/main.css
ShiyanlouNosqlJiaochengHeji20160904/css/normalize.css
ShiyanlouNosqlJiaochengHeji20160904/css/popup.css
ShiyanlouNosqlJiaochengHeji20160904/font/__init__.py
ShiyanlouNosqlJiaochengHeji20160904/font/fontello.eot
ShiyanlouNosqlJiaochengHeji20160904/font/fontello.svg
ShiyanlouNosqlJiaochengHeji20160904/font/fontello.ttf
ShiyanlouNosqlJiaochengHeji20160904/font/fontello.woff
ShiyanlouNosqlJiaochengHeji20160904/img/__init__.py
ShiyanlouNosqlJiaochengHeji20160904/img/annotator-glyph-sprite.png
ShiyanlouNosqlJiaochengHeji20160904/img/annotator-icon-sprite.png
ShiyanlouNosqlJiaochengHeji20160904/img/apple-touch-icon.png
ShiyanlouNosqlJiaochengHeji20160904/img/cancelfullscreen.png
ShiyanlouNosqlJiaochengHeji20160904/img/close.png
ShiyanlouNosqlJiaochengHeji20160904/img/fullscreen.png
ShiyanlouNosqlJiaochengHeji20160904/img/loader.gif
ShiyanlouNosqlJiaochengHeji20160904/img/menu-icon.png
ShiyanlouNosqlJiaochengHeji20160904/img/save.png
ShiyanlouNosqlJiaochengHeji20160904/img/saved.png
ShiyanlouNosqlJiaochengHeji20160904/img/settings-s.png
ShiyanlouNosqlJiaochengHeji20160904/img/settings.png
ShiyanlouNosqlJiaochengHeji20160904/img/star.png
ShiyanlouNosqlJiaochengHeji20160904/js/__init__.py
ShiyanlouNosqlJiaochengHeji20160904/js/epub.js
ShiyanlouNosqlJiaochengHeji20160904/js/epub.min.js
ShiyanlouNosqlJiaochengHeji20160904/js/epub.min.map
ShiyanlouNosqlJiaochengHeji20160904/js/hooks.min.js
ShiyanlouNosqlJiaochengHeji20160904/js/hooks.min.map
ShiyanlouNosqlJiaochengHeji20160904/js/reader.js
ShiyanlouNosqlJiaochengHeji20160904/js/reader.js.map
ShiyanlouNosqlJiaochengHeji20160904/js/reader.min.js
shiyanlou_nosql_jiaocheng_heji_20160904-2024.3.2.0.dist-info/METADATA
shiyanlou_nosql_jiaocheng_heji_20160904-2024.3.2.0.dist-info/WHEEL
shiyanlou_nosql_jiaocheng_heji_20160904-2024.3.2.0.dist-info/entry_points.txt
shiyanlou_nosql_jiaocheng_heji_20160904-2024.3.2.0.dist-info/top_level.txt
shiyanlou_nosql_jiaocheng_heji_20160904-2024.3.2.0.dist-info/RECORD
